flake8_translation_activate.py
flake8_translation_activate-1.0.2.dist-info/DESCRIPTION.rst
flake8_translation_activate-1.0.2.dist-info/METADATA
flake8_translation_activate-1.0.2.dist-info/RECORD
flake8_translation_activate-1.0.2.dist-info/WHEEL
flake8_translation_activate-1.0.2.dist-info/entry_points.txt
flake8_translation_activate-1.0.2.dist-info/metadata.json
flake8_translation_activate-1.0.2.dist-info/top_level.txt
