Metadata-Version: 2.0
Name: flake8-translation-activate
Version: 1.0.2
Summary: translation activate plugin for flake8
Home-page: https://github.com/unleashed/flake8-translation-activate
Author: Unleashed NV
Author-email: development@unleashed.be
License: MIT
Keywords: flake8 translation activate
Platform: UNKNOWN
Classifier: Development Status :: 3 - Alpha
Classifier: Environment :: Console
Classifier: Intended Audience :: Developers
Classifier: License :: OSI Approved :: MIT License
Classifier: Operating System :: OS Independent
Classifier: Programming Language :: Python
Classifier: Programming Language :: Python :: 2
Classifier: Programming Language :: Python :: 3
Classifier: Topic :: Software Development :: Libraries :: Python Modules
Classifier: Topic :: Software Development :: Quality Assurance
Requires-Dist: flake8
